no_recursion/__init__.py
no_recursion/no_recursion.py
no_recursion-1.0.3.dist-info/METADATA
no_recursion-1.0.3.dist-info/WHEEL
no_recursion-1.0.3.dist-info/top_level.txt
no_recursion-1.0.3.dist-info/RECORD
