Metadata-Version: 2.1
Name: no-recursion
Version: 1.0.3
Summary: This module helps you to get rid of recursions when you wantto rename a builtin function, or a function that already exists.
Home-page: https://github.com/jonatan1609/noRecursion
Author: Jonathan
Author-email: pybots.il@gmail.com
License: UNKNOWN
Platform: UNKNOWN
Classifier: License :: OSI Approved :: The Unlicense (Unlicense)
Classifier: Programming Language :: Python :: 3.5
Classifier: Operating System :: OS Independent
Requires-Python: >=3.5
